pynizima/NizimaPlugin.py
pynizima/NizimaRequest.py
pynizima/__init__.py
pynizima/errors.py
pynizima/events.py
pynizima/utils.py
pynizima-1.0.dist-info/LICENSE.md
pynizima-1.0.dist-info/METADATA
pynizima-1.0.dist-info/WHEEL
pynizima-1.0.dist-info/top_level.txt
pynizima-1.0.dist-info/RECORD
