Metadata-Version: 2.1
Name: pynizima
Version: 1.0
Summary: Python library for interacting with the NizimaLIVE API via WebSocket
Home-page: https://github.com/jellydreams/pynizima
Author: Jelly Dreams
Classifier: Programming Language :: Python :: 3
Classifier: License :: OSI Approved :: MIT License
Classifier: Operating System :: OS Independent
Requires-Python: >=3.10
License-File: LICENSE.md
